telethon/__init__.py
telethon/enums.py
telethon/events.py
telethon/sessions.py
telethon/version.py
telethon/_client/__init__.py
telethon/_client/account.py
telethon/_client/auth.py
telethon/_client/bots.py
telethon/_client/chats.py
telethon/_client/dialogs.py
telethon/_client/downloads.py
telethon/_client/messageparse.py
telethon/_client/messages.py
telethon/_client/telegrambaseclient.py
telethon/_client/telegramclient.py
telethon/_client/updates.py
telethon/_client/uploads.py
telethon/_client/users.py
telethon/_crypto/__init__.py
telethon/_crypto/aes.py
telethon/_crypto/aesctr.py
telethon/_crypto/authkey.py
telethon/_crypto/factorization.py
telethon/_crypto/libssl.py
telethon/_crypto/rsa.py
telethon/_events/__init__.py
telethon/_events/album.py
telethon/_events/base.py
telethon/_events/callbackquery.py
telethon/_events/chataction.py
telethon/_events/inlinequery.py
telethon/_events/messagedeleted.py
telethon/_events/messageedited.py
telethon/_events/messageread.py
telethon/_events/newmessage.py
telethon/_events/raw.py
telethon/_events/userupdate.py
telethon/_events/filters/__init__.py
telethon/_events/filters/base.py
telethon/_events/filters/entities.py
telethon/_events/filters/generic.py
telethon/_events/filters/messages.py
telethon/_misc/__init__.py
telethon/_misc/binaryreader.py
telethon/_misc/enums.py
telethon/_misc/helpers.py
telethon/_misc/hints.py
telethon/_misc/html.py
telethon/_misc/markdown.py
telethon/_misc/messagepacker.py
telethon/_misc/password.py
telethon/_misc/requestiter.py
telethon/_misc/tlobject.py
telethon/_misc/utils.py
telethon/_network/__init__.py
telethon/_network/authenticator.py
telethon/_network/connection.py
telethon/_network/mtprotoplainsender.py
telethon/_network/mtprotosender.py
telethon/_network/mtprotostate.py
telethon/_network/requeststate.py
telethon/_network/transports/__init__.py
telethon/_network/transports/abridged.py
telethon/_network/transports/full.py
telethon/_network/transports/intermediate.py
cloudgram_telethon-1.24.2.post1.dist-info/LICENSE
cloudgram_telethon-1.24.2.post1.dist-info/METADATA
cloudgram_telethon-1.24.2.post1.dist-info/WHEEL
cloudgram_telethon-1.24.2.post1.dist-info/top_level.txt
cloudgram_telethon-1.24.2.post1.dist-info/RECORD
