Metadata-Version: 2.1
Name: cloudgram-telethon
Version: 1.24.2.post1
Summary: Full-featured Telegram client library for Python 3
Home-page: https://github.com/Cloudygram-org/Telethon
Download-URL: https://github.com/Cloudygram-org/Telethon/releases
Author: Roberto Montalti
Author-email: roberto.montalti00@gmail.com
License: MIT
Keywords: telegram api chat client library messaging mtproto
Classifier: Development Status :: 5 - Production/Stable
Classifier: Intended Audience :: Developers
Classifier: Topic :: Communications :: Chat
Classifier: License :: OSI Approved :: MIT License
Classifier: Programming Language :: Python :: 3
Classifier: Programming Language :: Python :: 3.7
Classifier: Programming Language :: Python :: 3.8
Classifier: Programming Language :: Python :: 3.9
Classifier: Programming Language :: Python :: 3.10
Requires-Python: >=3.7
License-File: LICENSE
Requires-Dist: pyaes
Requires-Dist: rsa
Provides-Extra: cryptg
Requires-Dist: cryptg ; extra == 'cryptg'
